python_docs/__init__.py
python_docs/example.py
python_docs-0.1.0.dist-info/LICENSE
python_docs-0.1.0.dist-info/METADATA
python_docs-0.1.0.dist-info/WHEEL
python_docs-0.1.0.dist-info/top_level.txt
python_docs-0.1.0.dist-info/RECORD
