Metadata-Version: 2.2
Name: python-docs
Version: 0.1.0
Summary: A short description of your package
Author-email: Pegleg <pegleg@linux.com>
Project-URL: Homepage, https://github.com/p3gleg/python-docs
Project-URL: Bug Tracker, https://github.com/p3gleg/python-docs/issues
Classifier: Programming Language :: Python :: 3
Classifier: License :: OSI Approved :: MIT License
Classifier: Operating System :: OS Independent
Requires-Python: >=3.7
License-File: LICENSE
